ezcommit/__init__.py
ezcommit/cli.py
ezcommit/commit_generator.py
effort_zero_commit-0.1.3.dist-info/LICENSE
effort_zero_commit-0.1.3.dist-info/METADATA
effort_zero_commit-0.1.3.dist-info/WHEEL
effort_zero_commit-0.1.3.dist-info/entry_points.txt
effort_zero_commit-0.1.3.dist-info/top_level.txt
effort_zero_commit-0.1.3.dist-info/RECORD
