Metadata-Version: 2.2
Name: effort-zero-commit
Version: 0.1.3
Summary: Automated Git commit message generator using AI
Home-page: https://github.com/abderrahmanyouabd/ezcommit
Author: Abderrahman Youabd
Author-email: youabd50@gmail.com
Classifier: Development Status :: 3 - Alpha
Classifier: Intended Audience :: Developers
Classifier: License :: OSI Approved :: MIT License
Classifier: Programming Language :: Python :: 3
Classifier: Programming Language :: Python :: 3.7
Classifier: Programming Language :: Python :: 3.8
Classifier: Programming Language :: Python :: 3.9
Classifier: Programming Language :: Python :: 3.10
Requires-Python: >=3.9
License-File: LICENSE
Requires-Dist: gitpython
Requires-Dist: groq
Requires-Dist: python-dotenv
Requires-Dist: click
Requires-Dist: json-with-comments
Dynamic: author
Dynamic: author-email
Dynamic: classifier
Dynamic: description
Dynamic: description-content-type
Dynamic: home-page
Dynamic: requires-dist
Dynamic: requires-python
Dynamic: summary
